{"stats":{"minecraft:killed":{"minecraft:sheep":3,"minecraft:cow":2},"minecraft:custom":{"minecraft:time_since_rest":17200,"minecraft:play_time":17200,"minecraft:interact_with_furnace":1,"minecraft:sprint_one_cm":41,"minecraft:damage_taken":90,"minecraft:walk_one_cm":101760,"minecraft:walk_under_water_one_cm":121,"minecraft:mob_kills":5,"minecraft:jump":197,"minecraft:damage_dealt":445,"minecraft:leave_game":1,"minecraft:time_since_death":17200,"minecraft:walk_on_water_one_cm":3499,"minecraft:total_world_time":17200,"minecraft:interact_with_crafting_table":1,"minecraft:fall_one_cm":5595,"minecraft:fly_one_cm":322},"minecraft:picked_up":{"minecraft:stone_sword":1,"minecraft:leather":3,"minecraft:bow":1,"minecraft:wheat_seeds":18,"minecraft:acacia_log":5,"minecraft:beef":5,"minecraft:oak_log":2,"minecraft:mutton":4,"minecraft:white_wool":3},"minecraft:mined":{"minecraft:grass":123,"minecraft:oak_log":2,"minecraft:tall_grass":2},"minecraft:used":{"minecraft:stone_sword":113},"minecraft:crafted":{"minecraft:oak_planks":8,"minecraft:acacia_wood":3,"minecraft:acacia_planks":16,"minecraft:white_carpet":3,"minecraft:stick":8}},"DataVersion":2865}